setup.py
docs/INSTALL.txt
docs/LICENSE.GPL
docs/LICENSE.txt
plonehrm/__init__.py
plonehrm.notifications.egg-info/PKG-INFO
plonehrm.notifications.egg-info/SOURCES.txt
plonehrm.notifications.egg-info/dependency_links.txt
plonehrm.notifications.egg-info/entry_points.txt
plonehrm.notifications.egg-info/namespace_packages.txt
plonehrm.notifications.egg-info/not-zip-safe
plonehrm.notifications.egg-info/requires.txt
plonehrm.notifications.egg-info/top_level.txt
plonehrm/notifications/HISTORY.txt
plonehrm/notifications/README.txt
plonehrm/notifications/TODO.txt
plonehrm/notifications/__init__.py
plonehrm/notifications/adapters.py
plonehrm/notifications/browser.py
plonehrm/notifications/configure.zcml
plonehrm/notifications/emailer.py
plonehrm/notifications/events.py
plonehrm/notifications/interfaces.py
plonehrm/notifications/utils.py
plonehrm/notifications/version.txt
plonehrm/notifications/doc/technical.txt
plonehrm/notifications/tests/__init__.py
plonehrm/notifications/tests/test_unit.py